{"kind":"ARC#requestsDataExport","createdAt":"2016-10-12T22:03:57.846Z","version":"5.0.5-test","requests":[{"order":0,"url":"http://localhost/WebApiDemo/employee","method":"GET","type":"saved","updateTime":1476204815886,"id":279,"kind":"ARC#RequestObject","har":{"comment":"Created when making a request as a history object.","version":"1.2","creator":{"comment":"ARC for Google Chrome.","version":"5.0.5-test","name":"Advanced REST client"},"browser":{"version":"53.0.2785.143","name":"Chrome"},"pages":[{"startedDateTime":"2016-10-11T16:53:35.865Z","id":"GET:http://localhost/WebApiDemo/employee-0","title":"Get All Employees","pageTimings":{"onLoad":-1,"onContentLoad":-1}}],"entries":[{"startedDateTime":"2016-10-11T16:52:13.264Z","pageref":"GET:http://localhost/WebApiDemo/employee-0","time":22.459999999962747,"timings":{"blocked":-1,"connect":1.7399999999906868,"dns":-1,"receive":15.774999999906868,"send":2.6950000000651926,"wait":2.25},"cache":{"beforeRequest":null,"afterRequest":null},"request":{"method":"GET","url":"http://localhost/WebApiDemo/employee","httpVersion":"HTTP/1.1","headersSize":140,"bodySize":0,"postData":{"mimeType":"application/octet-stream","text":"","params":[]},"headers":[{"name":"Accept","value":"application/json"}],"queryString":[],"cookies":[]},"response":{"status":200,"statusText":"OK","httpVersion":"HTTP/1.1","redirectURL":"","headersSize":466,"bodySize":9910,"content":{"size":9910,"mimeType":"application/json","text":"[{\"Id\":1,\"FirstName\":\"Madilyn\",\"LastName\":\"Perry\",\"Department\":\"ACCOUNTING\",\"HireDateTime\":\"2010-03-03T09:00:00\",\"PhoneWork\":\"(555) 256-8171\",\"PhoneHome\":\"(555) 166-7267\",\"PhoneCell\":\"(555) 249-9452\"},{\"Id\":2,\"FirstName\":\"Gregory\",\"LastName\":\"Johnson\",\"Department\":\"MAINTENANCE\",\"HireDateTime\":\"2038-08-08T09:00:00\",\"PhoneWork\":\"(555) 979-5436\",\"PhoneHome\":\"(555) 429-1989\",\"PhoneCell\":\"(555) 767-4521\"},{\"Id\":3,\"FirstName\":\"Lance\",\"LastName\":\"Mccray\",\"Department\":\"PRODUCTION\",\"HireDateTime\":\"2030-10-21T09:00:00\",\"PhoneWork\":\"(555) 078-4627\",\"PhoneHome\":\"(555) 327-4519\",\"PhoneCell\":\"(555) 714-3459\"},{\"Id\":4,\"FirstName\":\"Chloe\",\"LastName\":\"Cobb\",\"Department\":\"PRODUCTION\",\"HireDateTime\":\"2027-12-18T09:00:00\",\"PhoneWork\":\"(555) 343-1532\",\"PhoneHome\":\"(555) 837-5501\",\"PhoneCell\":\"(555) 171-6994\"},{\"Id\":5,\"FirstName\":\"Summer\",\"LastName\":\"Pace\",\"Department\":\"MAINTENANCE\",\"HireDateTime\":\"2015-10-24T09:00:00\",\"PhoneWork\":\"(555) 731-0768\",\"PhoneHome\":\"(555) 723-1897\",\"PhoneCell\":\"(555) 185-6031\"},{\"Id\":6,\"FirstName\":\"Colin\",\"LastName\":\"Durham\",\"Department\":\"HR\",\"HireDateTime\":\"1991-09-28T09:00:00\",\"PhoneWork\":\"(555) 913-8095\",\"PhoneHome\":\"(555) 612-3813\",\"PhoneCell\":\"(555) 631-6489\"},{\"Id\":7,\"FirstName\":\"Sylas\",\"LastName\":\"Love\",\"Department\":\"HR\",\"HireDateTime\":\"2046-05-20T09:00:00\",\"PhoneWork\":\"(555) 091-5544\",\"PhoneHome\":\"(555) 288-6406\",\"PhoneCell\":\"(555) 580-9058\"},{\"Id\":8,\"FirstName\":\"Elliot\",\"LastName\":\"Hester\",\"Department\":\"PRODUCTION\",\"HireDateTime\":\"1978-08-08T09:00:00\",\"PhoneWork\":\"(555) 430-6485\",\"PhoneHome\":\"(555) 988-5466\",\"PhoneCell\":\"(555) 748-8220\"},{\"Id\":9,\"FirstName\":\"Noelle\",\"LastName\":\"Salazar\",\"Department\":\"PRODUCTION\",\"HireDateTime\":\"2009-02-12T09:00:00\",\"PhoneWork\":\"(555) 125-8130\",\"PhoneHome\":\"(555) 903-3274\",\"PhoneCell\":\"(555) 438-5643\"},{\"Id\":10,\"FirstName\":\"Aaliyah\",\"LastName\":\"Carson\",\"Department\":\"MAINTENANCE\",\"HireDateTime\":\"2028-01-27T09:00:00\",\"PhoneWork\":\"(555) 205-4364\",\"PhoneHome\":\"(555) 752-1133\",\"PhoneCell\":\"(555) 447-8865\"},{\"Id\":11,\"FirstName\":\"Osvaldo\",\"LastName\":\"Mcdaniel\",\"Department\":\"PRODUCTION\",\"HireDateTime\":\"2027-06-15T09:00:00\",\"PhoneWork\":\"(555) 567-8868\",\"PhoneHome\":\"(555) 177-3394\",\"PhoneCell\":\"(555) 355-9401\"},{\"Id\":12,\"FirstName\":\"Blaze\",\"LastName\":\"Mckay\",\"Department\":\"MANAGEMENT\",\"HireDateTime\":\"2031-06-05T09:00:00\",\"PhoneWork\":\"(555) 529-7859\",\"PhoneHome\":\"(555) 256-0349\",\"PhoneCell\":\"(555) 824-7479\"},{\"Id\":13,\"FirstName\":\"Mariyah\",\"LastName\":\"Mckee\",\"Department\":\"SALES\",\"HireDateTime\":\"2024-08-05T09:00:00\",\"PhoneWork\":\"(555) 749-4164\",\"PhoneHome\":\"(555) 557-4046\",\"PhoneCell\":\"(555) 379-5429\"},{\"Id\":14,\"FirstName\":\"Manuel\",\"LastName\":\"Nichols\",\"Department\":\"QA\",\"HireDateTime\":\"2022-07-17T09:00:00\",\"PhoneWork\":\"(555) 342-3413\",\"PhoneHome\":\"(555) 992-6497\",\"PhoneCell\":\"(555) 540-1522\"},{\"Id\":15,\"FirstName\":\"Iker\",\"LastName\":\"Gaines\",\"Department\":\"SALES\",\"HireDateTime\":\"2027-03-04T09:00:00\",\"PhoneWork\":\"(555) 649-8150\",\"PhoneHome\":\"(555) 788-1263\",\"PhoneCell\":\"(555) 929-0182\"},{\"Id\":16,\"FirstName\":\"Brennan\",\"LastName\":\"Harper\",\"Department\":\"MAINTENANCE\",\"HireDateTime\":\"1985-01-25T09:00:00\",\"PhoneWork\":\"(555) 557-8685\",\"PhoneHome\":\"(555) 503-6896\",\"PhoneCell\":\"(555) 438-3908\"},{\"Id\":17,\"FirstName\":\"Pierce\",\"LastName\":\"Mayer\",\"Department\":\"MAINTENANCE\",\"HireDateTime\":\"2000-02-21T09:00:00\",\"PhoneWork\":\"(555) 822-4576\",\"PhoneHome\":\"(555) 253-5844\",\"PhoneCell\":\"(555) 270-4601\"},{\"Id\":18,\"FirstName\":\"Raegan\",\"LastName\":\"Rivers\",\"Department\":\"QA\",\"HireDateTime\":\"2023-03-23T09:00:00\",\"PhoneWork\":\"(555) 355-5490\",\"PhoneHome\":\"(555) 735-4983\",\"PhoneCell\":\"(555) 601-1743\"},{\"Id\":19,\"FirstName\":\"Emely\",\"LastName\":\"Lane\",\"Department\":\"MAINTENANCE\",\"HireDateTime\":\"1997-06-09T09:00:00\",\"PhoneWork\":\"(555) 469-3294\",\"PhoneHome\":\"(555) 192-0551\",\"PhoneCell\":\"(555) 252-8883\"},{\"Id\":20,\"FirstName\":\"Hugo\",\"LastName\":\"Howe\",\"Department\":\"ACCOUNTING\",\"HireDateTime\":\"1990-07-07T09:00:00\",\"PhoneWork\":\"(555) 959-5072\",\"PhoneHome\":\"(555) 951-8376\",\"PhoneCell\":\"(555) 579-8474\"},{\"Id\":21,\"FirstName\":\"Dominique\",\"LastName\":\"Thompson\",\"Department\":\"MARKETING\",\"HireDateTime\":\"2045-08-04T09:00:00\",\"PhoneWork\":\"(555) 250-5541\",\"PhoneHome\":\"(555) 187-6327\",\"PhoneCell\":\"(555) 418-1080\"},{\"Id\":22,\"FirstName\":\"Emely\",\"LastName\":\"Morin\",\"Department\":\"MANAGEMENT\",\"HireDateTime\":\"2012-04-12T09:00:00\",\"PhoneWork\":\"(555) 011-9022\",\"PhoneHome\":\"(555) 891-2364\",\"PhoneCell\":\"(555) 680-6376\"},{\"Id\":23,\"FirstName\":\"Emmeline\",\"LastName\":\"Mccarty\",\"Department\":\"QA\",\"HireDateTime\":\"2034-03-24T09:00:00\",\"PhoneWork\":\"(555) 130-3514\",\"PhoneHome\":\"(555) 895-9186\",\"PhoneCell\":\"(555) 550-9095\"},{\"Id\":24,\"FirstName\":\"Sam\",\"LastName\":\"Stuart\",\"Department\":\"QA\",\"HireDateTime\":\"2006-12-05T09:00:00\",\"PhoneWork\":\"(555) 460-4856\",\"PhoneHome\":\"(555) 726-6257\",\"PhoneCell\":\"(555) 835-0854\"},{\"Id\":25,\"FirstName\":\"Jaden\",\"LastName\":\"Faulkner\",\"Department\":\"PRODUCTION\",\"HireDateTime\":\"2033-02-06T09:00:00\",\"PhoneWork\":\"(555) 090-6265\",\"PhoneHome\":\"(555) 040-3474\",\"PhoneCell\":\"(555) 257-8754\"}]"},"headers":[{"name":"cache-control","value":"no-cache"},{"name":"pragma","value":"no-cache"},{"name":"content-type","value":"application/json; charset=utf-8"},{"name":"expires","value":"-1"},{"name":"server","value":"Microsoft-IIS/10.0"},{"name":"x-aspnet-version","value":"4.0.30319"},{"name":"x-powered-by","value":"ASP.NET"},{"name":"date","value":"Tue, 11 Oct 2016 16:52:13 GMT"},{"name":"content-length","value":"4955"}],"cookies":[]}}]},"name":"Get All Employees"},{"order":0,"url":"http://localhost/WebApiDemo/employee/department/accounting","method":"GET","type":"saved","updateTime":1476204861068,"id":281,"kind":"ARC#RequestObject","har":{"comment":"Created when making a request as a history object.","version":"1.2","creator":{"comment":"ARC for Google Chrome.","version":"5.0.5-test","name":"Advanced REST client"},"browser":{"version":"53.0.2785.143","name":"Chrome"},"pages":[{"startedDateTime":"2016-10-11T16:54:21.051Z","id":"GET:http://localhost/WebApiDemo/employee/department/accounting-0","title":"Get Accounting Employees","pageTimings":{"onLoad":-1,"onContentLoad":-1}}],"entries":[{"startedDateTime":"2016-10-11T16:53:55.376Z","pageref":"GET:http://localhost/WebApiDemo/employee/department/accounting-0","time":55.735000000102445,"timings":{"blocked":-1,"connect":2.699999999953434,"dns":-1,"receive":15.745000000111759,"send":1.590000000083819,"wait":35.699999999953434},"cache":{"beforeRequest":null,"afterRequest":null},"request":{"method":"GET","url":"http://localhost/WebApiDemo/employee/department/accounting","httpVersion":"HTTP/1.1","headersSize":184,"bodySize":0,"postData":{"mimeType":"application/octet-stream","text":"","params":[]},"headers":[{"name":"Accept","value":"application/json"}],"queryString":[],"cookies":[]},"response":{"status":200,"statusText":"OK","httpVersion":"HTTP/1.1","redirectURL":"","headersSize":464,"bodySize":796,"content":{"size":796,"mimeType":"application/json","text":"[{\"Id\":1,\"FirstName\":\"Madilyn\",\"LastName\":\"Perry\",\"Department\":\"ACCOUNTING\",\"HireDateTime\":\"2010-03-03T09:00:00\",\"PhoneWork\":\"(555) 256-8171\",\"PhoneHome\":\"(555) 166-7267\",\"PhoneCell\":\"(555) 249-9452\"},{\"Id\":20,\"FirstName\":\"Hugo\",\"LastName\":\"Howe\",\"Department\":\"ACCOUNTING\",\"HireDateTime\":\"1990-07-07T09:00:00\",\"PhoneWork\":\"(555) 959-5072\",\"PhoneHome\":\"(555) 951-8376\",\"PhoneCell\":\"(555) 579-8474\"}]"},"headers":[{"name":"cache-control","value":"no-cache"},{"name":"pragma","value":"no-cache"},{"name":"content-type","value":"application/json; charset=utf-8"},{"name":"expires","value":"-1"},{"name":"server","value":"Microsoft-IIS/10.0"},{"name":"x-aspnet-version","value":"4.0.30319"},{"name":"x-powered-by","value":"ASP.NET"},{"name":"date","value":"Tue, 11 Oct 2016 16:53:55 GMT"},{"name":"content-length","value":"398"}],"cookies":[]}}]},"name":"Get Accounting Employees"},{"order":0,"url":"http://localhost/WebApiDemo/employee/name/mc","method":"GET","type":"saved","updateTime":1476205204896,"id":285,"kind":"ARC#RequestObject","har":{"comment":"Created when making a request as a history object.","version":"1.2","creator":{"comment":"ARC for Google Chrome.","version":"5.0.5-test","name":"Advanced REST client"},"browser":{"version":"53.0.2785.143","name":"Chrome"},"pages":[{"startedDateTime":"2016-10-11T17:00:04.879Z","id":"GET:http://localhost/WebApiDemo/employee/name/mc-0","title":"Employees Name Contains Mc","pageTimings":{"onLoad":-1,"onContentLoad":-1}}],"entries":[{"startedDateTime":"2016-10-11T16:59:44.325Z","pageref":"GET:http://localhost/WebApiDemo/employee/name/mc-0","time":17.450000000651926,"timings":{"blocked":-1,"connect":2.3350000004284084,"dns":-1,"receive":11.385000000242144,"send":0.8349999994970858,"wait":2.8950000004842877},"cache":{"beforeRequest":null,"afterRequest":null},"request":{"method":"GET","url":"http://localhost/WebApiDemo/employee/name/mc","httpVersion":"HTTP/1.1","headersSize":156,"bodySize":0,"postData":{"mimeType":"application/octet-stream","text":"","params":[]},"headers":[{"name":"Accept","value":"application/json"}],"queryString":[],"cookies":[]},"response":{"status":200,"statusText":"OK","httpVersion":"HTTP/1.1","redirectURL":"","headersSize":464,"bodySize":1990,"content":{"size":1990,"mimeType":"application/json","text":"[{\"Id\":3,\"FirstName\":\"Lance\",\"LastName\":\"Mccray\",\"Department\":\"PRODUCTION\",\"HireDateTime\":\"2030-10-21T09:00:00\",\"PhoneWork\":\"(555) 078-4627\",\"PhoneHome\":\"(555) 327-4519\",\"PhoneCell\":\"(555) 714-3459\"},{\"Id\":11,\"FirstName\":\"Osvaldo\",\"LastName\":\"Mcdaniel\",\"Department\":\"PRODUCTION\",\"HireDateTime\":\"2027-06-15T09:00:00\",\"PhoneWork\":\"(555) 567-8868\",\"PhoneHome\":\"(555) 177-3394\",\"PhoneCell\":\"(555) 355-9401\"},{\"Id\":12,\"FirstName\":\"Blaze\",\"LastName\":\"Mckay\",\"Department\":\"MANAGEMENT\",\"HireDateTime\":\"2031-06-05T09:00:00\",\"PhoneWork\":\"(555) 529-7859\",\"PhoneHome\":\"(555) 256-0349\",\"PhoneCell\":\"(555) 824-7479\"},{\"Id\":13,\"FirstName\":\"Mariyah\",\"LastName\":\"Mckee\",\"Department\":\"SALES\",\"HireDateTime\":\"2024-08-05T09:00:00\",\"PhoneWork\":\"(555) 749-4164\",\"PhoneHome\":\"(555) 557-4046\",\"PhoneCell\":\"(555) 379-5429\"},{\"Id\":23,\"FirstName\":\"Emmeline\",\"LastName\":\"Mccarty\",\"Department\":\"QA\",\"HireDateTime\":\"2034-03-24T09:00:00\",\"PhoneWork\":\"(555) 130-3514\",\"PhoneHome\":\"(555) 895-9186\",\"PhoneCell\":\"(555) 550-9095\"}]"},"headers":[{"name":"cache-control","value":"no-cache"},{"name":"pragma","value":"no-cache"},{"name":"content-type","value":"application/json; charset=utf-8"},{"name":"expires","value":"-1"},{"name":"server","value":"Microsoft-IIS/10.0"},{"name":"x-aspnet-version","value":"4.0.30319"},{"name":"x-powered-by","value":"ASP.NET"},{"name":"date","value":"Tue, 11 Oct 2016 16:59:44 GMT"},{"name":"content-length","value":"995"}],"cookies":[]}}]},"name":"Employees Name Contains Mc"},{"order":0,"url":"http://localhost/WebApiDemo/employee/4","method":"GET","type":"saved","updateTime":1476207293973,"id":287,"kind":"ARC#RequestObject","har":{"comment":"Created when making a request as a history object.","version":"1.2","creator":{"comment":"ARC for Google Chrome.","version":"5.0.5-test","name":"Advanced REST client"},"browser":{"version":"53.0.2785.143","name":"Chrome"},"pages":[{"startedDateTime":"2016-10-11T17:34:53.950Z","id":"GET:http://localhost/WebApiDemo/employee/4-0","title":"Get Employee 4","pageTimings":{"onLoad":-1,"onContentLoad":-1}}],"entries":[{"startedDateTime":"2016-10-11T17:34:34.919Z","pageref":"GET:http://localhost/WebApiDemo/employee/4-0","time":56.690000001341105,"timings":{"blocked":-1,"connect":1.4550000010058284,"dns":-1,"receive":9.945000000298023,"send":11.875,"wait":33.41500000003725},"cache":{"beforeRequest":null,"afterRequest":null},"request":{"method":"GET","url":"http://localhost/WebApiDemo/employee/4","httpVersion":"HTTP/1.1","headersSize":144,"bodySize":0,"postData":{"mimeType":"application/octet-stream","text":"","params":[]},"headers":[{"name":"Accept","value":"application/json"}],"queryString":[],"cookies":[]},"response":{"status":200,"statusText":"OK","httpVersion":"HTTP/1.1","redirectURL":"","headersSize":464,"bodySize":392,"content":{"size":392,"mimeType":"application/json","text":"{\"Id\":4,\"FirstName\":\"Chloe\",\"LastName\":\"Cobb\",\"Department\":\"PRODUCTION\",\"HireDateTime\":\"2027-12-18T09:00:00\",\"PhoneWork\":\"(555) 343-1532\",\"PhoneHome\":\"(555) 837-5501\",\"PhoneCell\":\"(555) 171-6994\"}"},"headers":[{"name":"cache-control","value":"no-cache"},{"name":"pragma","value":"no-cache"},{"name":"content-type","value":"application/json; charset=utf-8"},{"name":"expires","value":"-1"},{"name":"server","value":"Microsoft-IIS/10.0"},{"name":"x-aspnet-version","value":"4.0.30319"},{"name":"x-powered-by","value":"ASP.NET"},{"name":"date","value":"Tue, 11 Oct 2016 17:34:34 GMT"},{"name":"content-length","value":"196"}],"cookies":[]}}]},"name":"Get Employee 4"},{"order":0,"url":"http://localhost/WebApiDemo/employee/100","method":"GET","type":"saved","updateTime":1476207314432,"id":289,"kind":"ARC#RequestObject","har":{"comment":"Created when making a request as a history object.","version":"1.2","creator":{"comment":"ARC for Google Chrome.","version":"5.0.5-test","name":"Advanced REST client"},"browser":{"version":"53.0.2785.143","name":"Chrome"},"pages":[{"startedDateTime":"2016-10-11T17:35:14.415Z","id":"GET:http://localhost/WebApiDemo/employee/100-0","title":"Get Employee 100 (Not Found)","pageTimings":{"onLoad":-1,"onContentLoad":-1}}],"entries":[{"startedDateTime":"2016-10-11T17:35:00.971Z","pageref":"GET:http://localhost/WebApiDemo/employee/100-0","time":30.685000001452863,"timings":{"blocked":-1,"connect":1.5800000000745058,"dns":-1,"receive":11.360000001266599,"send":1.2900000009685755,"wait":16.454999999143183},"cache":{"beforeRequest":null,"afterRequest":null},"request":{"method":"GET","url":"http://localhost/WebApiDemo/employee/100","httpVersion":"HTTP/1.1","headersSize":148,"bodySize":0,"postData":{"mimeType":"application/octet-stream","text":"","params":[]},"headers":[{"name":"Accept","value":"application/json"}],"queryString":[],"cookies":[]},"response":{"status":404,"statusText":"Not Found","httpVersion":"HTTP/1.1","redirectURL":"","headersSize":462,"bodySize":66,"content":{"size":66,"mimeType":"application/json","text":"{\"Message\":\"Employee not found!\"}"},"headers":[{"name":"cache-control","value":"no-cache"},{"name":"pragma","value":"no-cache"},{"name":"content-type","value":"application/json; charset=utf-8"},{"name":"expires","value":"-1"},{"name":"server","value":"Microsoft-IIS/10.0"},{"name":"x-aspnet-version","value":"4.0.30319"},{"name":"x-powered-by","value":"ASP.NET"},{"name":"date","value":"Tue, 11 Oct 2016 17:35:00 GMT"},{"name":"content-length","value":"33"}],"cookies":[]}}]},"name":"Get Employee 100 (Not Found)"},{"order":0,"url":"http://localhost/WebApiDemo/employee","method":"POST","type":"saved","referenceEntry":4,"updateTime":1476294780167,"id":290,"kind":"ARC#RequestObject","har":{"comment":"Created when making a request as a history object.","version":"1.2","creator":{"comment":"ARC for Google Chrome.","version":"5.0.5-test","name":"Advanced REST client"},"browser":{"version":"53.0.2785.143","name":"Chrome"},"pages":[{"startedDateTime":"2016-10-11T18:49:52.402Z","id":"POST:http://localhost/WebApiDemo/employee-0","title":"Create Employee 1000","pageTimings":{"onLoad":-1,"onContentLoad":-1}},{"startedDateTime":"2016-10-11T18:49:55.918Z","id":"POST:http://localhost/WebApiDemo/employee-1","title":"Create Employee 1000","pageTimings":{"onLoad":-1,"onContentLoad":-1}},{"startedDateTime":"2016-10-11T18:50:50.293Z","id":"POST:http://localhost/WebApiDemo/employee-2","title":"Create Employee 1000","pageTimings":{"onLoad":-1,"onContentLoad":-1}},{"startedDateTime":"2016-10-11T18:51:23.356Z","id":"POST:http://localhost/WebApiDemo/employee-3","title":"Create Employee 1000","pageTimings":{"onLoad":-1,"onContentLoad":-1}},{"startedDateTime":"2016-10-11T18:51:23.361Z","id":"POST:http://localhost/WebApiDemo/employee-4","title":"Create Employee 1000","pageTimings":{"onLoad":-1,"onContentLoad":-1}},{"startedDateTime":"2016-10-11T18:51:24.679Z","id":"POST:http://localhost/WebApiDemo/employee-5","title":"Create Employee 1000","pageTimings":{"onLoad":-1,"onContentLoad":-1}},{"startedDateTime":"2016-10-11T18:52:24.054Z","id":"POST:http://localhost/WebApiDemo/employee-6","title":"Create Employee 1000","pageTimings":{"onLoad":-1,"onContentLoad":-1}},{"startedDateTime":"2016-10-11T19:03:30.811Z","id":"POST:http://localhost/WebApiDemo/employee-7","title":"Create Employee 1000","pageTimings":{"onLoad":-1,"onContentLoad":-1}},{"startedDateTime":"2016-10-11T20:34:16.983Z","id":"POST:http://localhost/WebApiDemo/employee-8","title":"Create Employee 1000","pageTimings":{"onLoad":-1,"onContentLoad":-1}},{"startedDateTime":"2016-10-11T20:51:34.783Z","id":"POST:http://localhost/WebApiDemo/employee-9","title":"Create Employee 1000","pageTimings":{"onLoad":-1,"onContentLoad":-1}},{"startedDateTime":"2016-10-11T21:04:10.861Z","id":"POST:http://localhost/WebApiDemo/employee-10","title":"Create Employee 1000","pageTimings":{"onLoad":-1,"onContentLoad":-1}},{"startedDateTime":"2016-10-11T21:09:55.797Z","id":"POST:http://localhost/WebApiDemo/employee-11","title":"Create Employee 1000","pageTimings":{"onLoad":-1,"onContentLoad":-1}},{"startedDateTime":"2016-10-11T21:15:45.495Z","id":"POST:http://localhost/WebApiDemo/employee-12","title":"Create Employee 1000","pageTimings":{"onLoad":-1,"onContentLoad":-1}},{"startedDateTime":"2016-10-11T21:16:15.654Z","id":"POST:http://localhost/WebApiDemo/employee-13","title":"Create Employee 1000","pageTimings":{"onLoad":-1,"onContentLoad":-1}},{"startedDateTime":"2016-10-11T21:20:13.903Z","id":"POST:http://localhost/WebApiDemo/employee-14","title":"Create Employee 1000","pageTimings":{"onLoad":-1,"onContentLoad":-1}},{"startedDateTime":"2016-10-12T17:51:44.133Z","id":"POST:http://localhost/WebApiDemo/employee-15","title":"Create Employee 1000","pageTimings":{"onLoad":-1,"onContentLoad":-1}},{"startedDateTime":"2016-10-12T17:52:04.251Z","id":"POST:http://localhost/WebApiDemo/employee-16","title":"Create Employee 1000","pageTimings":{"onLoad":-1,"onContentLoad":-1}},{"startedDateTime":"2016-10-12T17:52:34.866Z","id":"POST:http://localhost/WebApiDemo/employee-17","title":"Create Employee 1000","pageTimings":{"onLoad":-1,"onContentLoad":-1}},{"startedDateTime":"2016-10-12T17:53:00.151Z","id":"POST:http://localhost/WebApiDemo/employee-18","title":"Create Employee 1000","pageTimings":{"onLoad":-1,"onContentLoad":-1}}],"entries":[{"startedDateTime":"2016-10-11T18:30:16.254Z","pageref":"POST:http://localhost/WebApiDemo/employee-0","time":62.90499999932945,"timings":{"blocked":-1,"connect":1.559999999590218,"dns":-1,"receive":10.759999999776483,"send":0.9399999994784594,"wait":49.64500000048429},"cache":{"beforeRequest":null,"afterRequest":null},"request":{"method":"POST","url":"http://localhost/WebApiDemo/employee","httpVersion":"HTTP/1.1","headersSize":154,"bodySize":776,"postData":{"mimeType":"application/json","text":"{\n\"Id\": 1000\n\"FirstName\": \"Alan\"\n\"LastName\": \"Newbeguy\"\n\"Department\": \"PRODUCTION\"\n\"HireDateTime\": \"2016-10-11T11:46:00\"\n\"PhoneWork\": \"(555) 322-4455\"\n\"PhoneHome\": \"(555) 844-5664\"\n\"PhoneCell\": \"(555) 322-3395\"\n\"EmployeeType\": 2\n\"DateOfBirth\": \"1964-07-19T00:00:00\"\n\"Email\": \"alan.newbeguy@yahoo.com\"\n\"StreetAddress\": \"602 Mill Street\"\n\"City\": \"Roseville\"\n\"State\": \"CA\"\n\"ZipCode\": 95747\n}","params":[]},"headers":[{"name":"Content-Type","value":"application/json"}],"queryString":[],"cookies":[]},"response":{"status":200,"statusText":"OK","httpVersion":"HTTP/1.1","redirectURL":"","headersSize":464,"bodySize":728,"content":{"size":728,"mimeType":"application/json","text":"{\"Id\":4,\"FirstName\":\"Chloe\",\"LastName\":\"Cobb\",\"Department\":\"PRODUCTION\",\"HireDateTime\":\"2027-12-18T09:00:00\",\"PhoneWork\":\"(555) 343-1532\",\"PhoneHome\":\"(555) 837-5501\",\"PhoneCell\":\"(555) 171-6994\",\"EmployeeType\":1,\"DateOfBirth\":\"1984-12-09T00:00:00\",\"Email\":\"chloe.cobb@outlook.com\",\"StreetAddress\":\"8240 Walnut Avenue\",\"City\":\"Corona\",\"State\":\"CA\",\"ZipCode\":36551}"},"headers":[{"name":"cache-control","value":"no-cache"},{"name":"pragma","value":"no-cache"},{"name":"content-type","value":"application/json; charset=utf-8"},{"name":"expires","value":"-1"},{"name":"server","value":"Microsoft-IIS/10.0"},{"name":"x-aspnet-version","value":"4.0.30319"},{"name":"x-powered-by","value":"ASP.NET"},{"name":"date","value":"Tue, 11 Oct 2016 18:30:16 GMT"},{"name":"content-length","value":"364"}],"cookies":[]}},{"startedDateTime":"2016-10-11T18:49:55.712Z","pageref":1,"time":119.4700000025332,"timings":{"blocked":-1,"connect":1.6400000005960464,"dns":-1,"receive":10.870000001043081,"send":2.599999999627471,"wait":104.3600000012666},"cache":{"beforeRequest":null,"afterRequest":null},"request":{"method":"POST","url":"http://localhost/WebApiDemo/employee","httpVersion":"HTTP/1.1","headersSize":154,"bodySize":776,"postData":{"mimeType":"application/json","text":"{\n\"Id\": 1000\n\"FirstName\": \"Alan\"\n\"LastName\": \"Newbeguy\"\n\"Department\": \"PRODUCTION\"\n\"HireDateTime\": \"2016-10-11T11:46:00\"\n\"PhoneWork\": \"(555) 322-4455\"\n\"PhoneHome\": \"(555) 844-5664\"\n\"PhoneCell\": \"(555) 322-3395\"\n\"EmployeeType\": 2\n\"DateOfBirth\": \"1964-07-19T00:00:00\"\n\"Email\": \"alan.newbeguy@yahoo.com\"\n\"StreetAddress\": \"602 Mill Street\"\n\"City\": \"Roseville\"\n\"State\": \"CA\"\n\"ZipCode\": 95747\n}","params":[]},"headers":[{"name":"Content-Type","value":"application/json"}],"queryString":[],"cookies":[]},"response":{"status":400,"statusText":"Bad Request","httpVersion":"HTTP/1.1","redirectURL":"","headersSize":464,"bodySize":342,"content":{"size":342,"mimeType":"application/json","text":"{\"Message\":\"The request is invalid.\",\"ModelState\":{\"newEmployee.Id\":[\"After parsing a value an unexpected character was encountered: \\\". Path 'Id', line 3, position 1.\"]}}"},"headers":[{"name":"cache-control","value":"no-cache"},{"name":"pragma","value":"no-cache"},{"name":"content-type","value":"application/json; charset=utf-8"},{"name":"expires","value":"-1"},{"name":"server","value":"Microsoft-IIS/10.0"},{"name":"x-aspnet-version","value":"4.0.30319"},{"name":"x-powered-by","value":"ASP.NET"},{"name":"date","value":"Tue, 11 Oct 2016 18:49:55 GMT"},{"name":"content-length","value":"171"}],"cookies":[]}},{"startedDateTime":"2016-10-11T18:50:50.207Z","pageref":2,"time":18.625,"timings":{"blocked":-1,"connect":1.7200000006705523,"dns":-1,"receive":10.824999999254942,"send":0.9600000008940697,"wait":5.119999999180436},"cache":{"beforeRequest":null,"afterRequest":null},"request":{"method":"POST","url":"http://localhost/WebApiDemo/employee","httpVersion":"HTTP/1.1","headersSize":154,"bodySize":754,"postData":{"mimeType":"application/json","text":"{\n\"FirstName\": \"Alan\"\n\"LastName\": \"Newbeguy\"\n\"Department\": \"PRODUCTION\"\n\"HireDateTime\": \"2016-10-11T11:46:00\"\n\"PhoneWork\": \"(555) 322-4455\"\n\"PhoneHome\": \"(555) 844-5664\"\n\"PhoneCell\": \"(555) 322-3395\"\n\"EmployeeType\": 2\n\"DateOfBirth\": \"1964-07-19T00:00:00\"\n\"Email\": \"alan.newbeguy@yahoo.com\"\n\"StreetAddress\": \"602 Mill Street\"\n\"City\": \"Roseville\"\n\"State\": \"CA\"\n\"ZipCode\": 95747\n}","params":[]},"headers":[{"name":"Content-Type","value":"application/json"}],"queryString":[],"cookies":[]},"response":{"status":400,"statusText":"Bad Request","httpVersion":"HTTP/1.1","redirectURL":"","headersSize":464,"bodySize":370,"content":{"size":370,"mimeType":"application/json","text":"{\"Message\":\"The request is invalid.\",\"ModelState\":{\"newEmployee.FirstName\":[\"After parsing a value an unexpected character was encountered: \\\". Path 'FirstName', line 3, position 1.\"]}}"},"headers":[{"name":"cache-control","value":"no-cache"},{"name":"pragma","value":"no-cache"},{"name":"content-type","value":"application/json; charset=utf-8"},{"name":"expires","value":"-1"},{"name":"server","value":"Microsoft-IIS/10.0"},{"name":"x-aspnet-version","value":"4.0.30319"},{"name":"x-powered-by","value":"ASP.NET"},{"name":"date","value":"Tue, 11 Oct 2016 18:50:49 GMT"},{"name":"content-length","value":"185"}],"cookies":[]}},{"startedDateTime":"2016-10-11T18:50:50.207Z","pageref":3,"time":18.625,"timings":{"blocked":-1,"connect":1.7200000006705523,"dns":-1,"receive":10.824999999254942,"send":0.9600000008940697,"wait":5.119999999180436},"cache":{"beforeRequest":null,"afterRequest":null},"request":{"method":"POST","url":"http://localhost/WebApiDemo/employee","httpVersion":"HTTP/1.1","headersSize":154,"bodySize":804,"postData":{"mimeType":"application/json","text":"{\n\"Id\": 1000,\n\"FirstName\": \"Alan\",\n\"LastName\": \"Newbeguy\",\n\"Department\": \"PRODUCTION\",\n\"HireDateTime\": \"2016-10-11T11:46:00\",\n\"PhoneWork\": \"(555) 322-4455\",\n\"PhoneHome\": \"(555) 844-5664\",\n\"PhoneCell\": \"(555) 322-3395\",\n\"EmployeeType\": 2,\n\"DateOfBirth\": \"1964-07-19T00:00:00\",\n\"Email\": \"alan.newbeguy@yahoo.com\",\n\"StreetAddress\": \"602 Mill Street\",\n\"City\": \"Roseville\",\n\"State\": \"CA\",\n\"ZipCode\": 95747\n}","params":[]},"headers":[{"name":"Content-Type","value":"application/json"}],"queryString":[],"cookies":[]},"response":{"status":400,"statusText":"Bad Request","httpVersion":"HTTP/1.1","redirectURL":"","headersSize":464,"bodySize":370,"content":{"size":370,"mimeType":"application/json","text":"{\"Message\":\"The request is invalid.\",\"ModelState\":{\"newEmployee.FirstName\":[\"After parsing a value an unexpected character was encountered: \\\". Path 'FirstName', line 3, position 1.\"]}}"},"headers":[{"name":"cache-control","value":"no-cache"},{"name":"pragma","value":"no-cache"},{"name":"content-type","value":"application/json; charset=utf-8"},{"name":"expires","value":"-1"},{"name":"server","value":"Microsoft-IIS/10.0"},{"name":"x-aspnet-version","value":"4.0.30319"},{"name":"x-powered-by","value":"ASP.NET"},{"name":"date","value":"Tue, 11 Oct 2016 18:50:49 GMT"},{"name":"content-length","value":"185"}],"cookies":[]}},{"startedDateTime":"2016-10-11T18:50:50.207Z","pageref":4,"time":18.625,"timings":{"blocked":-1,"connect":1.7200000006705523,"dns":-1,"receive":10.824999999254942,"send":0.9600000008940697,"wait":5.119999999180436},"cache":{"beforeRequest":null,"afterRequest":null},"request":{"method":"POST","url":"http://localhost/WebApiDemo/employee","httpVersion":"HTTP/1.1","headersSize":154,"bodySize":804,"postData":{"mimeType":"application/json","text":"{\n\"Id\": 1000,\n\"FirstName\": \"Alan\",\n\"LastName\": \"Newbeguy\",\n\"Department\": \"PRODUCTION\",\n\"HireDateTime\": \"2016-10-11T11:46:00\",\n\"PhoneWork\": \"(555) 322-4455\",\n\"PhoneHome\": \"(555) 844-5664\",\n\"PhoneCell\": \"(555) 322-3395\",\n\"EmployeeType\": 2,\n\"DateOfBirth\": \"1964-07-19T00:00:00\",\n\"Email\": \"alan.newbeguy@yahoo.com\",\n\"StreetAddress\": \"602 Mill Street\",\n\"City\": \"Roseville\",\n\"State\": \"CA\",\n\"ZipCode\": 95747\n}","params":[]},"headers":[{"name":"Content-Type","value":"application/json"}],"queryString":[],"cookies":[]},"response":{"status":400,"statusText":"Bad Request","httpVersion":"HTTP/1.1","redirectURL":"","headersSize":464,"bodySize":370,"content":{"size":370,"mimeType":"application/json","text":"{\"Message\":\"The request is invalid.\",\"ModelState\":{\"newEmployee.FirstName\":[\"After parsing a value an unexpected character was encountered: \\\". Path 'FirstName', line 3, position 1.\"]}}"},"headers":[{"name":"cache-control","value":"no-cache"},{"name":"pragma","value":"no-cache"},{"name":"content-type","value":"application/json; charset=utf-8"},{"name":"expires","value":"-1"},{"name":"server","value":"Microsoft-IIS/10.0"},{"name":"x-aspnet-version","value":"4.0.30319"},{"name":"x-powered-by","value":"ASP.NET"},{"name":"date","value":"Tue, 11 Oct 2016 18:50:49 GMT"},{"name":"content-length","value":"185"}],"cookies":[]}},{"startedDateTime":"2016-10-11T18:51:24.503Z","pageref":5,"time":122.3899999987334,"timings":{"blocked":-1,"connect":1.6000000014901161,"dns":-1,"receive":9.129999997094274,"send":2.9799999985843897,"wait":108.68000000156462},"cache":{"beforeRequest":null,"afterRequest":null},"request":{"method":"POST","url":"http://localhost/WebApiDemo/employee","httpVersion":"HTTP/1.1","headersSize":154,"bodySize":804,"postData":{"mimeType":"application/json","text":"{\n\"Id\": 1000,\n\"FirstName\": \"Alan\",\n\"LastName\": \"Newbeguy\",\n\"Department\": \"PRODUCTION\",\n\"HireDateTime\": \"2016-10-11T11:46:00\",\n\"PhoneWork\": \"(555) 322-4455\",\n\"PhoneHome\": \"(555) 844-5664\",\n\"PhoneCell\": \"(555) 322-3395\",\n\"EmployeeType\": 2,\n\"DateOfBirth\": \"1964-07-19T00:00:00\",\n\"Email\": \"alan.newbeguy@yahoo.com\",\n\"StreetAddress\": \"602 Mill Street\",\n\"City\": \"Roseville\",\n\"State\": \"CA\",\n\"ZipCode\": 95747\n}","params":[]},"headers":[{"name":"Content-Type","value":"application/json"}],"queryString":[],"cookies":[]},"response":{"status":201,"statusText":"Created","httpVersion":"HTTP/1.1","redirectURL":"","headersSize":472,"bodySize":0,"content":{"size":0,"mimeType":"application/octet-stream","text":""},"headers":[{"name":"cache-control","value":"no-cache"},{"name":"pragma","value":"no-cache"},{"name":"expires","value":"-1"},{"name":"location","value":"http://localhost/WebApiDemo/employee/1000"},{"name":"server","value":"Microsoft-IIS/10.0"},{"name":"x-aspnet-version","value":"4.0.30319"},{"name":"x-powered-by","value":"ASP.NET"},{"name":"date","value":"Tue, 11 Oct 2016 18:51:24 GMT"},{"name":"content-length","value":"0"}],"cookies":[]}},{"startedDateTime":"2016-10-11T18:52:23.897Z","pageref":6,"time":39.14499999769032,"timings":{"blocked":-1,"connect":1.5649999976158142,"dns":-1,"receive":25.345000000670552,"send":1.574999999254942,"wait":10.660000000149012},"cache":{"beforeRequest":null,"afterRequest":null},"request":{"method":"POST","url":"http://localhost/WebApiDemo/employee","httpVersion":"HTTP/1.1","headersSize":154,"bodySize":804,"postData":{"mimeType":"application/json","text":"{\n\"Id\": 1000,\n\"FirstName\": \"Alan\",\n\"LastName\": \"Newbeguy\",\n\"Department\": \"PRODUCTION\",\n\"HireDateTime\": \"2016-10-11T11:46:00\",\n\"PhoneWork\": \"(555) 322-4455\",\n\"PhoneHome\": \"(555) 844-5664\",\n\"PhoneCell\": \"(555) 322-3395\",\n\"EmployeeType\": 2,\n\"DateOfBirth\": \"1964-07-19T00:00:00\",\n\"Email\": \"alan.newbeguy@yahoo.com\",\n\"StreetAddress\": \"602 Mill Street\",\n\"City\": \"Roseville\",\n\"State\": \"CA\",\n\"ZipCode\": 95747\n}","params":[]},"headers":[{"name":"Content-Type","value":"application/json"}],"queryString":[],"cookies":[]},"response":{"status":500,"statusText":"Internal Server Error","httpVersion":"HTTP/1.1","redirectURL":"","headersSize":466,"bodySize":3770,"content":{"size":3770,"mimeType":"application/json","text":"{\"Message\":\"An error has occurred.\",\"ExceptionMessage\":\"Duplicate key specified\",\"ExceptionType\":\"Synergex.SynergyDE.DuplicateException\",\"StackTrace\":\"   at Synergex.SynergyDE.SysRoutines.iostore(Int32 chn, AlphaDesc rec)\\r\\n   at WebApiServices.Controllers.EmployeeController.PostCreateEmployee(Employee newEmployee) in C:\\\\DEV\\\\PRIVATE\\\\WebApiDemo\\\\WebApiServices\\\\Controllers\\\\EmployeeDemo.dbl:line 144\\r\\n   at lambda_method(Closure , Object , Object[] )\\r\\n   at System.Web.Http.Controllers.ReflectedHttpActionDescriptor.ActionExecutor.<>c__DisplayClass10.<GetExecutor>b__9(Object instance, Object[] methodParameters)\\r\\n   at System.Web.Http.Controllers.ReflectedHttpActionDescriptor.ExecuteAsync(HttpControllerContext controllerContext, IDictionary`2 arguments, CancellationToken cancellationToken)\\r\\n--- End of stack trace from previous location where exception was thrown ---\\r\\n   at System.Runtime.CompilerServices.TaskAwaiter.ThrowForNonSuccess(Task task)\\r\\n   at System.Runtime.CompilerServices.TaskAwaiter.HandleNonSuccessAndDebuggerNotification(Task task)\\r\\n   at System.Web.Http.Controllers.ApiControllerActionInvoker.<InvokeActionAsyncCore>d__0.MoveNext()\\r\\n--- End of stack trace from previous location where exception was thrown ---\\r\\n   at System.Runtime.CompilerServices.TaskAwaiter.ThrowForNonSuccess(Task task)\\r\\n   at System.Runtime.CompilerServices.TaskAwaiter.HandleNonSuccessAndDebuggerNotification(Task task)\\r\\n   at System.Web.Http.Controllers.ActionFilterResult.<ExecuteAsync>d__2.MoveNext()\\r\\n--- End of stack trace from previous location where exception was thrown ---\\r\\n   at System.Runtime.CompilerServices.TaskAwaiter.ThrowForNonSuccess(Task task)\\r\\n   at System.Runtime.CompilerServices.TaskAwaiter.HandleNonSuccessAndDebuggerNotification(Task task)\\r\\n   at System.Web.Http.Dispatcher.HttpControllerDispatcher.<SendAsync>d__1.MoveNext()\"}"},"headers":[{"name":"cache-control","value":"no-cache"},{"name":"pragma","value":"no-cache"},{"name":"content-type","value":"application/json; charset=utf-8"},{"name":"expires","value":"-1"},{"name":"server","value":"Microsoft-IIS/10.0"},{"name":"x-aspnet-version","value":"4.0.30319"},{"name":"x-powered-by","value":"ASP.NET"},{"name":"date","value":"Tue, 11 Oct 2016 18:52:23 GMT"},{"name":"content-length","value":"1885"}],"cookies":[]}},{"startedDateTime":"2016-10-11T19:03:30.568Z","pageref":7,"time":170.22499999776483,"timings":{"blocked":-1,"connect":1.3849999997764826,"dns":-1,"receive":9.034999998286366,"send":0.974999999627471,"wait":158.8300000000745},"cache":{"beforeRequest":null,"afterRequest":null},"request":{"method":"POST","url":"http://localhost/WebApiDemo/employee","httpVersion":"HTTP/1.1","headersSize":154,"bodySize":804,"postData":{"mimeType":"application/json","text":"{\n\"Id\": 1000,\n\"FirstName\": \"Alan\",\n\"LastName\": \"Newbeguy\",\n\"Department\": \"PRODUCTION\",\n\"HireDateTime\": \"2016-10-11T11:46:00\",\n\"PhoneWork\": \"(555) 322-4455\",\n\"PhoneHome\": \"(555) 844-5664\",\n\"PhoneCell\": \"(555) 322-3395\",\n\"EmployeeType\": 2,\n\"DateOfBirth\": \"1964-07-19T00:00:00\",\n\"Email\": \"alan.newbeguy@yahoo.com\",\n\"StreetAddress\": \"602 Mill Street\",\n\"City\": \"Roseville\",\n\"State\": \"CA\",\n\"ZipCode\": 95747\n}","params":[]},"headers":[{"name":"Content-Type","value":"application/json"}],"queryString":[],"cookies":[]},"response":{"status":201,"statusText":"Created","httpVersion":"HTTP/1.1","redirectURL":"","headersSize":472,"bodySize":0,"content":{"size":0,"mimeType":"application/octet-stream","text":""},"headers":[{"name":"cache-control","value":"no-cache"},{"name":"pragma","value":"no-cache"},{"name":"expires","value":"-1"},{"name":"location","value":"http://localhost/WebApiDemo/employee/1000"},{"name":"server","value":"Microsoft-IIS/10.0"},{"name":"x-aspnet-version","value":"4.0.30319"},{"name":"x-powered-by","value":"ASP.NET"},{"name":"date","value":"Tue, 11 Oct 2016 19:03:30 GMT"},{"name":"content-length","value":"0"}],"cookies":[]}},{"startedDateTime":"2016-10-11T20:34:16.694Z","pageref":8,"time":222.82000000029802,"timings":{"blocked":-1,"connect":1.550000000745058,"dns":-1,"receive":8.529999999329448,"send":0.9100000001490116,"wait":211.8300000000745},"cache":{"beforeRequest":null,"afterRequest":null},"request":{"method":"POST","url":"http://localhost/WebApiDemo/employee","httpVersion":"HTTP/1.1","headersSize":154,"bodySize":804,"postData":{"mimeType":"application/json","text":"{\n\"Id\": 1000,\n\"FirstName\": \"Alan\",\n\"LastName\": \"Newbeguy\",\n\"Department\": \"PRODUCTION\",\n\"HireDateTime\": \"2016-10-11T11:46:00\",\n\"PhoneWork\": \"(555) 322-4455\",\n\"PhoneHome\": \"(555) 844-5664\",\n\"PhoneCell\": \"(555) 322-3395\",\n\"EmployeeType\": 2,\n\"DateOfBirth\": \"1964-07-19T00:00:00\",\n\"Email\": \"alan.newbeguy@yahoo.com\",\n\"StreetAddress\": \"602 Mill Street\",\n\"City\": \"Roseville\",\n\"State\": \"CA\",\n\"ZipCode\": 95747\n}","params":[]},"headers":[{"name":"Content-Type","value":"application/json"}],"queryString":[],"cookies":[]},"response":{"status":201,"statusText":"Created","httpVersion":"HTTP/1.1","redirectURL":"","headersSize":472,"bodySize":0,"content":{"size":0,"mimeType":"application/octet-stream","text":""},"headers":[{"name":"cache-control","value":"no-cache"},{"name":"pragma","value":"no-cache"},{"name":"expires","value":"-1"},{"name":"location","value":"http://localhost/WebApiDemo/employee/1000"},{"name":"server","value":"Microsoft-IIS/10.0"},{"name":"x-aspnet-version","value":"4.0.30319"},{"name":"x-powered-by","value":"ASP.NET"},{"name":"date","value":"Tue, 11 Oct 2016 20:34:16 GMT"},{"name":"content-length","value":"0"}],"cookies":[]}},{"startedDateTime":"2016-10-11T20:51:34.517Z","pageref":9,"time":195.13000000081956,"timings":{"blocked":-1,"connect":1.3900000024586916,"dns":-1,"receive":9.56499999947846,"send":1.4999999981373549,"wait":182.67500000074506},"cache":{"beforeRequest":null,"afterRequest":null},"request":{"method":"POST","url":"http://localhost/WebApiDemo/employee","httpVersion":"HTTP/1.1","headersSize":154,"bodySize":804,"postData":{"mimeType":"application/json","text":"{\n\"Id\": 1000,\n\"FirstName\": \"Alan\",\n\"LastName\": \"Newbeguy\",\n\"Department\": \"PRODUCTION\",\n\"HireDateTime\": \"2016-10-11T11:46:00\",\n\"PhoneWork\": \"(555) 322-4455\",\n\"PhoneHome\": \"(555) 844-5664\",\n\"PhoneCell\": \"(555) 322-3395\",\n\"EmployeeType\": 2,\n\"DateOfBirth\": \"1964-07-19T00:00:00\",\n\"Email\": \"alan.newbeguy@yahoo.com\",\n\"StreetAddress\": \"602 Mill Street\",\n\"City\": \"Roseville\",\n\"State\": \"CA\",\n\"ZipCode\": 95747\n}","params":[]},"headers":[{"name":"Content-Type","value":"application/json"}],"queryString":[],"cookies":[]},"response":{"status":201,"statusText":"Created","httpVersion":"HTTP/1.1","redirectURL":"","headersSize":472,"bodySize":0,"content":{"size":0,"mimeType":"application/octet-stream","text":""},"headers":[{"name":"cache-control","value":"no-cache"},{"name":"pragma","value":"no-cache"},{"name":"expires","value":"-1"},{"name":"location","value":"http://localhost/WebApiDemo/employee/1000"},{"name":"server","value":"Microsoft-IIS/10.0"},{"name":"x-aspnet-version","value":"4.0.30319"},{"name":"x-powered-by","value":"ASP.NET"},{"name":"date","value":"Tue, 11 Oct 2016 20:51:34 GMT"},{"name":"content-length","value":"0"}],"cookies":[]}},{"startedDateTime":"2016-10-11T21:04:10.763Z","pageref":10,"time":26.62499999627471,"timings":{"blocked":-1,"connect":2.3849999979138374,"dns":-1,"receive":10.515000000596046,"send":0.8549999967217445,"wait":12.870000001043081},"cache":{"beforeRequest":null,"afterRequest":null},"request":{"method":"POST","url":"http://localhost/WebApiDemo/employee","httpVersion":"HTTP/1.1","headersSize":154,"bodySize":732,"postData":{"mimeType":"application/json","text":"{\n\"FirstName\": \"Alan\",\n\"Department\": \"PRODUCTION\",\n\"HireDateTime\": \"2016-10-11T11:46:00\",\n\"PhoneWork\": \"(555) 322-4455\",\n\"PhoneHome\": \"(555) 844-5664\",\n\"PhoneCell\": \"(555) 322-3395\",\n\"EmployeeType\": 2,\n\"DateOfBirth\": \"1964-07-19T00:00:00\",\n\"Email\": \"alan.newbeguy@yahoo.com\",\n\"StreetAddress\": \"602 Mill Street\",\n\"City\": \"Roseville\",\n\"State\": \"CA\",\n\"ZipCode\": 95747\n}","params":[]},"headers":[{"name":"Content-Type","value":"application/json"}],"queryString":[],"cookies":[]},"response":{"status":400,"statusText":"Bad Request","httpVersion":"HTTP/1.1","redirectURL":"","headersSize":464,"bodySize":402,"content":{"size":402,"mimeType":"application/json","text":"{\"Message\":\"The request is invalid.\",\"ModelState\":{\"newEmployee\":[\"Required property 'Id' not found in JSON. Path '', line 15, position 2.\"],\"newEmployee.LastName\":[\"The LastName field is required.\"]}}"},"headers":[{"name":"cache-control","value":"no-cache"},{"name":"pragma","value":"no-cache"},{"name":"content-type","value":"application/json; charset=utf-8"},{"name":"expires","value":"-1"},{"name":"server","value":"Microsoft-IIS/10.0"},{"name":"x-aspnet-version","value":"4.0.30319"},{"name":"x-powered-by","value":"ASP.NET"},{"name":"date","value":"Tue, 11 Oct 2016 21:04:10 GMT"},{"name":"content-length","value":"201"}],"cookies":[]}},{"startedDateTime":"2016-10-11T21:09:41.176Z","pageref":11,"time":14549.584999997169,"timings":{"blocked":-1,"connect":1.1849999986588955,"dns":-1,"receive":9.754999998956919,"send":0.8450000025331974,"wait":14537.79999999702},"cache":{"beforeRequest":null,"afterRequest":null},"request":{"method":"POST","url":"http://localhost/WebApiDemo/employee","httpVersion":"HTTP/1.1","headersSize":154,"bodySize":732,"postData":{"mimeType":"application/json","text":"{\n\"FirstName\": \"Alan\",\n\"Department\": \"PRODUCTION\",\n\"HireDateTime\": \"2016-10-11T11:46:00\",\n\"PhoneWork\": \"(555) 322-4455\",\n\"PhoneHome\": \"(555) 844-5664\",\n\"PhoneCell\": \"(555) 322-3395\",\n\"EmployeeType\": 2,\n\"DateOfBirth\": \"1964-07-19T00:00:00\",\n\"Email\": \"alan.newbeguy@yahoo.com\",\n\"StreetAddress\": \"602 Mill Street\",\n\"City\": \"Roseville\",\n\"State\": \"CA\",\n\"ZipCode\": 95747\n}","params":[]},"headers":[{"name":"Content-Type","value":"application/json"}],"queryString":[],"cookies":[]},"response":{"status":400,"statusText":"Bad Request","httpVersion":"HTTP/1.1","redirectURL":"","headersSize":464,"bodySize":402,"content":{"size":402,"mimeType":"application/json","text":"{\"Message\":\"The request is invalid.\",\"ModelState\":{\"newEmployee\":[\"Required property 'Id' not found in JSON. Path '', line 15, position 2.\"],\"newEmployee.LastName\":[\"The LastName field is required.\"]}}"},"headers":[{"name":"cache-control","value":"no-cache"},{"name":"pragma","value":"no-cache"},{"name":"content-type","value":"application/json; charset=utf-8"},{"name":"expires","value":"-1"},{"name":"server","value":"Microsoft-IIS/10.0"},{"name":"x-aspnet-version","value":"4.0.30319"},{"name":"x-powered-by","value":"ASP.NET"},{"name":"date","value":"Tue, 11 Oct 2016 21:09:55 GMT"},{"name":"content-length","value":"201"}],"cookies":[]}},{"startedDateTime":"2016-10-11T21:15:45.257Z","pageref":12,"time":169.8200000040233,"timings":{"blocked":-1,"connect":1.5850000008940697,"dns":-1,"receive":8.035000000149012,"send":0.9100000038743019,"wait":159.28999999910593},"cache":{"beforeRequest":null,"afterRequest":null},"request":{"method":"POST","url":"http://localhost/WebApiDemo/employee","httpVersion":"HTTP/1.1","headersSize":154,"bodySize":804,"postData":{"mimeType":"application/json","text":"{\n\"Id\": 1000,\n\"FirstName\": \"Alan\",\n\"LastName\": \"Newbeguy\",\n\"Department\": \"PRODUCTION\",\n\"HireDateTime\": \"2016-10-11T11:46:00\",\n\"PhoneWork\": \"(555) 322-4455\",\n\"PhoneHome\": \"(555) 844-5664\",\n\"PhoneCell\": \"(555) 322-3395\",\n\"EmployeeType\": 2,\n\"DateOfBirth\": \"1964-07-19T00:00:00\",\n\"Email\": \"alan.newbeguy@yahoo.com\",\n\"StreetAddress\": \"602 Mill Street\",\n\"City\": \"Roseville\",\n\"State\": \"CA\",\n\"ZipCode\": 95747\n}","params":[]},"headers":[{"name":"Content-Type","value":"application/json"}],"queryString":[],"cookies":[]},"response":{"status":201,"statusText":"Created","httpVersion":"HTTP/1.1","redirectURL":"","headersSize":472,"bodySize":0,"content":{"size":0,"mimeType":"application/octet-stream","text":""},"headers":[{"name":"cache-control","value":"no-cache"},{"name":"pragma","value":"no-cache"},{"name":"expires","value":"-1"},{"name":"location","value":"http://localhost/WebApiDemo/employee/1000"},{"name":"server","value":"Microsoft-IIS/10.0"},{"name":"x-aspnet-version","value":"4.0.30319"},{"name":"x-powered-by","value":"ASP.NET"},{"name":"date","value":"Tue, 11 Oct 2016 21:15:45 GMT"},{"name":"content-length","value":"0"}],"cookies":[]}},{"startedDateTime":"2016-10-11T21:16:15.520Z","pageref":13,"time":45.58499999716878,"timings":{"blocked":-1,"connect":1.6049999967217445,"dns":-1,"receive":10.95999999716878,"send":1.0600000023841858,"wait":31.96000000089407},"cache":{"beforeRequest":null,"afterRequest":null},"request":{"method":"POST","url":"http://localhost/WebApiDemo/employee","httpVersion":"HTTP/1.1","headersSize":154,"bodySize":738,"postData":{"mimeType":"application/json","text":"{\n\"LastName\": \"Newbeguy\",\n\"Department\": \"PRODUCTION\",\n\"HireDateTime\": \"2016-10-11T11:46:00\",\n\"PhoneWork\": \"(555) 322-4455\",\n\"PhoneHome\": \"(555) 844-5664\",\n\"PhoneCell\": \"(555) 322-3395\",\n\"EmployeeType\": 2,\n\"DateOfBirth\": \"1964-07-19T00:00:00\",\n\"Email\": \"alan.newbeguy@yahoo.com\",\n\"StreetAddress\": \"602 Mill Street\",\n\"City\": \"Roseville\",\n\"State\": \"CA\",\n\"ZipCode\": 95747\n}","params":[]},"headers":[{"name":"Content-Type","value":"application/json"}],"queryString":[],"cookies":[]},"response":{"status":400,"statusText":"Bad Request","httpVersion":"HTTP/1.1","redirectURL":"","headersSize":464,"bodySize":406,"content":{"size":406,"mimeType":"application/json","text":"{\"Message\":\"The request is invalid.\",\"ModelState\":{\"newEmployee\":[\"Required property 'Id' not found in JSON. Path '', line 15, position 2.\"],\"newEmployee.FirstName\":[\"The FirstName field is required.\"]}}"},"headers":[{"name":"cache-control","value":"no-cache"},{"name":"pragma","value":"no-cache"},{"name":"content-type","value":"application/json; charset=utf-8"},{"name":"expires","value":"-1"},{"name":"server","value":"Microsoft-IIS/10.0"},{"name":"x-aspnet-version","value":"4.0.30319"},{"name":"x-powered-by","value":"ASP.NET"},{"name":"date","value":"Tue, 11 Oct 2016 21:16:15 GMT"},{"name":"content-length","value":"203"}],"cookies":[]}},{"startedDateTime":"2016-10-11T21:19:59.086Z","pageref":14,"time":14750.769999999553,"timings":{"blocked":-1,"connect":1.3599999994039536,"dns":-1,"receive":7.955000001937151,"send":0.9050000011920929,"wait":14740.54999999702},"cache":{"beforeRequest":null,"afterRequest":null},"request":{"method":"POST","url":"http://localhost/WebApiDemo/employee","httpVersion":"HTTP/1.1","headersSize":154,"bodySize":804,"postData":{"mimeType":"application/json","text":"{\n\"Id\": 1000,\n\"FirstName\": \"Alan\",\n\"LastName\": \"Newbeguy\",\n\"Department\": \"PRODUCTION\",\n\"HireDateTime\": \"2016-10-11T11:46:00\",\n\"PhoneWork\": \"(555) 322-4455\",\n\"PhoneHome\": \"(555) 844-5664\",\n\"PhoneCell\": \"(555) 322-3395\",\n\"EmployeeType\": 2,\n\"DateOfBirth\": \"1964-07-19T00:00:00\",\n\"Email\": \"alan.newbeguy@yahoo.com\",\n\"StreetAddress\": \"602 Mill Street\",\n\"City\": \"Roseville\",\n\"State\": \"CA\",\n\"ZipCode\": 95747\n}","params":[]},"headers":[{"name":"Content-Type","value":"application/json"}],"queryString":[],"cookies":[]},"response":{"status":201,"statusText":"Created","httpVersion":"HTTP/1.1","redirectURL":"","headersSize":472,"bodySize":0,"content":{"size":0,"mimeType":"application/octet-stream","text":""},"headers":[{"name":"cache-control","value":"no-cache"},{"name":"pragma","value":"no-cache"},{"name":"expires","value":"-1"},{"name":"location","value":"http://localhost/WebApiDemo/employee/1000"},{"name":"server","value":"Microsoft-IIS/10.0"},{"name":"x-aspnet-version","value":"4.0.30319"},{"name":"x-powered-by","value":"ASP.NET"},{"name":"date","value":"Tue, 11 Oct 2016 21:20:13 GMT"},{"name":"content-length","value":"0"}],"cookies":[]}},{"startedDateTime":"2016-10-12T17:51:43.863Z","pageref":15,"time":202.3100000023842,"timings":{"blocked":-1,"connect":1.9950000047683716,"dns":-1,"receive":8.665000006556511,"send":7.790000006556511,"wait":183.8599999845028},"cache":{"beforeRequest":null,"afterRequest":null},"request":{"method":"POST","url":"http://localhost/WebApiDemo/employee","httpVersion":"HTTP/1.1","headersSize":154,"bodySize":804,"postData":{"mimeType":"application/json","text":"{\n\"Id\": 1000,\n\"FirstName\": \"Alan\",\n\"LastName\": \"Newbeguy\",\n\"Department\": \"PRODUCTION\",\n\"HireDateTime\": \"2016-10-11T11:46:00\",\n\"PhoneWork\": \"(555) 322-4455\",\n\"PhoneHome\": \"(555) 844-5664\",\n\"PhoneCell\": \"(555) 322-3395\",\n\"EmployeeType\": 2,\n\"DateOfBirth\": \"1964-07-19T00:00:00\",\n\"Email\": \"alan.newbeguy@yahoo.com\",\n\"StreetAddress\": \"602 Mill Street\",\n\"City\": \"Roseville\",\n\"State\": \"CA\",\n\"ZipCode\": 95747\n}","params":[]},"headers":[{"name":"Content-Type","value":"application/json"}],"queryString":[],"cookies":[]},"response":{"status":201,"statusText":"Created","httpVersion":"HTTP/1.1","redirectURL":"","headersSize":472,"bodySize":0,"content":{"size":0,"mimeType":"application/octet-stream","text":""},"headers":[{"name":"cache-control","value":"no-cache"},{"name":"pragma","value":"no-cache"},{"name":"expires","value":"-1"},{"name":"location","value":"http://localhost/WebApiDemo/employee/1000"},{"name":"server","value":"Microsoft-IIS/10.0"},{"name":"x-aspnet-version","value":"4.0.30319"},{"name":"x-powered-by","value":"ASP.NET"},{"name":"date","value":"Wed, 12 Oct 2016 17:51:44 GMT"},{"name":"content-length","value":"0"}],"cookies":[]}},{"startedDateTime":"2016-10-12T17:52:04.141Z","pageref":16,"time":31.75500001013279,"timings":{"blocked":-1,"connect":1.969999998807907,"dns":-1,"receive":11.189999997615814,"send":0.8300000131130219,"wait":17.765000000596046},"cache":{"beforeRequest":null,"afterRequest":null},"request":{"method":"POST","url":"http://localhost/WebApiDemo/employee","httpVersion":"HTTP/1.1","headersSize":154,"bodySize":756,"postData":{"mimeType":"application/json","text":"{\n\"Id\": 1000,\n\"FirstName\": \"Alan\",\n\"Department\": \"PRODUCTION\",\n\"HireDateTime\": \"2016-10-11T11:46:00\",\n\"PhoneWork\": \"(555) 322-4455\",\n\"PhoneHome\": \"(555) 844-5664\",\n\"PhoneCell\": \"(555) 322-3395\",\n\"EmployeeType\": 2,\n\"DateOfBirth\": \"1964-07-19T00:00:00\",\n\"Email\": \"alan.newbeguy@yahoo.com\",\n\"StreetAddress\": \"602 Mill Street\",\n\"City\": \"Roseville\",\n\"State\": \"CA\",\n\"ZipCode\": 95747\n}","params":[]},"headers":[{"name":"Content-Type","value":"application/json"}],"queryString":[],"cookies":[]},"response":{"status":400,"statusText":"Bad Request","httpVersion":"HTTP/1.1","redirectURL":"","headersSize":464,"bodySize":222,"content":{"size":222,"mimeType":"application/json","text":"{\"Message\":\"The request is invalid.\",\"ModelState\":{\"newEmployee.LastName\":[\"The LastName field is required.\"]}}"},"headers":[{"name":"cache-control","value":"no-cache"},{"name":"pragma","value":"no-cache"},{"name":"content-type","value":"application/json; charset=utf-8"},{"name":"expires","value":"-1"},{"name":"server","value":"Microsoft-IIS/10.0"},{"name":"x-aspnet-version","value":"4.0.30319"},{"name":"x-powered-by","value":"ASP.NET"},{"name":"date","value":"Wed, 12 Oct 2016 17:52:04 GMT"},{"name":"content-length","value":"111"}],"cookies":[]}},{"startedDateTime":"2016-10-12T17:52:34.774Z","pageref":17,"time":14.965000003576279,"timings":{"blocked":-1,"connect":1.260000005364418,"dns":-1,"receive":10.600000008940697,"send":0.9749999940395355,"wait":2.1299999952316284},"cache":{"beforeRequest":null,"afterRequest":null},"request":{"method":"POST","url":"http://localhost/WebApiDemo/employee","httpVersion":"HTTP/1.1","headersSize":154,"bodySize":856,"postData":{"mimeType":"application/json","text":"{\n\"Id\": 1000,\n\"FirstName\": \"Alan\",\n\"LastName\": \"Newbeguysjdfghjsgdhfjgsjdfgjsghdfs\",\n\"Department\": \"PRODUCTION\",\n\"HireDateTime\": \"2016-10-11T11:46:00\",\n\"PhoneWork\": \"(555) 322-4455\",\n\"PhoneHome\": \"(555) 844-5664\",\n\"PhoneCell\": \"(555) 322-3395\",\n\"EmployeeType\": 2,\n\"DateOfBirth\": \"1964-07-19T00:00:00\",\n\"Email\": \"alan.newbeguy@yahoo.com\",\n\"StreetAddress\": \"602 Mill Street\",\n\"City\": \"Roseville\",\n\"State\": \"CA\",\n\"ZipCode\": 95747\n}","params":[]},"headers":[{"name":"Content-Type","value":"application/json"}],"queryString":[],"cookies":[]},"response":{"status":400,"statusText":"Bad Request","httpVersion":"HTTP/1.1","redirectURL":"","headersSize":464,"bodySize":288,"content":{"size":288,"mimeType":"application/json","text":"{\"Message\":\"The request is invalid.\",\"ModelState\":{\"newEmployee.LastName\":[\"The field LastName must be a string with a maximum length of 20.\"]}}"},"headers":[{"name":"cache-control","value":"no-cache"},{"name":"pragma","value":"no-cache"},{"name":"content-type","value":"application/json; charset=utf-8"},{"name":"expires","value":"-1"},{"name":"server","value":"Microsoft-IIS/10.0"},{"name":"x-aspnet-version","value":"4.0.30319"},{"name":"x-powered-by","value":"ASP.NET"},{"name":"date","value":"Wed, 12 Oct 2016 17:52:34 GMT"},{"name":"content-length","value":"144"}],"cookies":[]}},{"startedDateTime":"2016-10-12T17:53:00.060Z","pageref":18,"time":27.390000000596046,"timings":{"blocked":-1,"connect":1.375,"dns":-1,"receive":9.290000006556511,"send":0.9000000059604645,"wait":15.824999988079071},"cache":{"beforeRequest":null,"afterRequest":null},"request":{"method":"POST","url":"http://localhost/WebApiDemo/employee","httpVersion":"HTTP/1.1","headersSize":154,"bodySize":804,"postData":{"mimeType":"application/json","text":"{\n\"Id\": 1000,\n\"FirstName\": \"Alan\",\n\"LastName\": \"Newbeguy\",\n\"Department\": \"PRODUCTION\",\n\"HireDateTime\": \"2016-10-11T11:46:00\",\n\"PhoneWork\": \"(555) 322-4455\",\n\"PhoneHome\": \"(555) 844-5664\",\n\"PhoneCell\": \"(555) 322-3395\",\n\"EmployeeType\": 2,\n\"DateOfBirth\": \"1964-07-19T00:00:00\",\n\"Email\": \"alan.newbeguy@yahoo.com\",\n\"StreetAddress\": \"602 Mill Street\",\n\"City\": \"Roseville\",\n\"State\": \"CA\",\n\"ZipCode\": 95747\n}","params":[]},"headers":[{"name":"Content-Type","value":"application/json"}],"queryString":[],"cookies":[]},"response":{"status":201,"statusText":"Created","httpVersion":"HTTP/1.1","redirectURL":"","headersSize":472,"bodySize":0,"content":{"size":0,"mimeType":"application/octet-stream","text":""},"headers":[{"name":"cache-control","value":"no-cache"},{"name":"pragma","value":"no-cache"},{"name":"expires","value":"-1"},{"name":"location","value":"http://localhost/WebApiDemo/employee/1000"},{"name":"server","value":"Microsoft-IIS/10.0"},{"name":"x-aspnet-version","value":"4.0.30319"},{"name":"x-powered-by","value":"ASP.NET"},{"name":"date","value":"Wed, 12 Oct 2016 17:53:00 GMT"},{"name":"content-length","value":"0"}],"cookies":[]}}]},"name":"Create Employee 1000"},{"order":0,"url":"http://localhost/WebApiDemo/employee/1000","method":"GET","type":"saved","updateTime":1476211937637,"id":292,"kind":"ARC#RequestObject","har":{"comment":"Created when making a request as a history object.","version":"1.2","creator":{"comment":"ARC for Google Chrome.","version":"5.0.5-test","name":"Advanced REST client"},"browser":{"version":"53.0.2785.143","name":"Chrome"},"pages":[{"startedDateTime":"2016-10-11T18:52:17.620Z","id":"GET:http://localhost/WebApiDemo/employee/1000-0","title":"Get Employee 1000","pageTimings":{"onLoad":-1,"onContentLoad":-1}}],"entries":[{"startedDateTime":"2016-10-11T18:51:47.418Z","pageref":"GET:http://localhost/WebApiDemo/employee/1000-0","time":16.179999999701977,"timings":{"blocked":-1,"connect":1.3699999991804361,"dns":-1,"receive":11.304999999701977,"send":0.8450000006705523,"wait":2.6600000001490116},"cache":{"beforeRequest":null,"afterRequest":null},"request":{"method":"GET","url":"http://localhost/WebApiDemo/employee/1000","httpVersion":"HTTP/1.1","headersSize":150,"bodySize":0,"postData":{"mimeType":"application/octet-stream","text":"","params":[]},"headers":[{"name":"Accept","value":"application/json"}],"queryString":[],"cookies":[]},"response":{"status":404,"statusText":"Not Found","httpVersion":"HTTP/1.1","redirectURL":"","headersSize":462,"bodySize":66,"content":{"size":66,"mimeType":"application/json","text":"{\"Message\":\"Employee not found!\"}"},"headers":[{"name":"cache-control","value":"no-cache"},{"name":"pragma","value":"no-cache"},{"name":"content-type","value":"application/json; charset=utf-8"},{"name":"expires","value":"-1"},{"name":"server","value":"Microsoft-IIS/10.0"},{"name":"x-aspnet-version","value":"4.0.30319"},{"name":"x-powered-by","value":"ASP.NET"},{"name":"date","value":"Tue, 11 Oct 2016 18:51:47 GMT"},{"name":"content-length","value":"33"}],"cookies":[]}}]},"name":"Get Employee 1000"},{"order":0,"url":"http://localhost/WebApiDemo/employee/1000","method":"DELETE","type":"saved","updateTime":1476294711574,"id":293,"kind":"ARC#RequestObject","har":{"comment":"Created when making a request as a history object.","version":"1.2","creator":{"comment":"ARC for Google Chrome.","version":"5.0.5-test","name":"Advanced REST client"},"browser":{"version":"53.0.2785.143","name":"Chrome"},"pages":[{"startedDateTime":"2016-10-11T20:26:53.011Z","id":"DELETE:http://localhost/WebApiDemo/employee/1000-0","title":"Delete Employee 1000","pageTimings":{"onLoad":-1,"onContentLoad":-1}},{"startedDateTime":"2016-10-11T20:26:56.283Z","id":"DELETE:http://localhost/WebApiDemo/employee/1000-1","title":"Delete Employee 1000","pageTimings":{"onLoad":-1,"onContentLoad":-1}},{"startedDateTime":"2016-10-11T20:34:34.114Z","id":"DELETE:http://localhost/WebApiDemo/employee/1000-2","title":"Delete Employee 1000","pageTimings":{"onLoad":-1,"onContentLoad":-1}},{"startedDateTime":"2016-10-11T21:03:50.178Z","id":"DELETE:http://localhost/WebApiDemo/employee/1000-3","title":"Delete Employee 1000","pageTimings":{"onLoad":-1,"onContentLoad":-1}},{"startedDateTime":"2016-10-11T21:03:54.592Z","id":"DELETE:http://localhost/WebApiDemo/employee/1000-4","title":"Delete Employee 1000","pageTimings":{"onLoad":-1,"onContentLoad":-1}},{"startedDateTime":"2016-10-11T21:16:07.332Z","id":"DELETE:http://localhost/WebApiDemo/employee/1000-5","title":"Delete Employee 1000","pageTimings":{"onLoad":-1,"onContentLoad":-1}},{"startedDateTime":"2016-10-11T21:20:50.208Z","id":"DELETE:http://localhost/WebApiDemo/employee/1000-6","title":"Delete Employee 1000","pageTimings":{"onLoad":-1,"onContentLoad":-1}},{"startedDateTime":"2016-10-12T17:51:51.562Z","id":"DELETE:http://localhost/WebApiDemo/employee/1000-7","title":"Delete Employee 1000","pageTimings":{"onLoad":-1,"onContentLoad":-1}}],"entries":[{"startedDateTime":"2016-10-11T20:26:18.152Z","pageref":"DELETE:http://localhost/WebApiDemo/employee/1000-0","time":60.875000001862645,"timings":{"blocked":-1,"connect":1.550000000745058,"dns":-1,"receive":9.904999999329448,"send":0.9150000009685755,"wait":48.505000000819564},"cache":{"beforeRequest":null,"afterRequest":null},"request":{"method":"DELETE","url":"http://localhost/WebApiDemo/employee/1000","httpVersion":"HTTP/1.1","headersSize":110,"bodySize":0,"postData":{"mimeType":"application/x-www-form-urlencoded","text":"","params":[]},"headers":[],"queryString":[],"cookies":[]},"response":{"status":200,"statusText":"OK","httpVersion":"HTTP/1.1","redirectURL":"","headersSize":464,"bodySize":742,"content":{"size":742,"mimeType":"application/json","text":"{\"Id\":1000,\"FirstName\":\"Alan\",\"LastName\":\"Newbeguy\",\"Department\":\"PRODUCTION\",\"HireDateTime\":\"2016-10-11T11:46:00\",\"PhoneWork\":\"(555) 322-4455\",\"PhoneHome\":\"(555) 844-5664\",\"PhoneCell\":\"(555) 322-3395\",\"EmployeeType\":2,\"DateOfBirth\":\"1964-07-19T00:00:00\",\"Email\":\"alan.newbeguy@yahoo.com\",\"StreetAddress\":\"602 Mill Street\",\"City\":\"Roseville\",\"State\":\"CA\",\"ZipCode\":95747}"},"headers":[{"name":"cache-control","value":"no-cache"},{"name":"pragma","value":"no-cache"},{"name":"content-type","value":"application/json; charset=utf-8"},{"name":"expires","value":"-1"},{"name":"server","value":"Microsoft-IIS/10.0"},{"name":"x-aspnet-version","value":"4.0.30319"},{"name":"x-powered-by","value":"ASP.NET"},{"name":"date","value":"Tue, 11 Oct 2016 20:26:18 GMT"},{"name":"content-length","value":"371"}],"cookies":[]}},{"startedDateTime":"2016-10-11T20:26:56.193Z","pageref":1,"time":41.06999999843538,"timings":{"blocked":-1,"connect":1.4949999991804361,"dns":-1,"receive":9.290000000968575,"send":0.8149999994784594,"wait":29.469999998807907},"cache":{"beforeRequest":null,"afterRequest":null},"request":{"method":"DELETE","url":"http://localhost/WebApiDemo/employee/1000","httpVersion":"HTTP/1.1","headersSize":110,"bodySize":0,"postData":{"mimeType":"application/x-www-form-urlencoded","text":"","params":[]},"headers":[],"queryString":[],"cookies":[]},"response":{"status":200,"statusText":"OK","httpVersion":"HTTP/1.1","redirectURL":"","headersSize":368,"bodySize":0,"content":{"size":0,"mimeType":"application/octet-stream","text":""},"headers":[{"name":"cache-control","value":"no-cache"},{"name":"pragma","value":"no-cache"},{"name":"expires","value":"-1"},{"name":"server","value":"Microsoft-IIS/10.0"},{"name":"x-aspnet-version","value":"4.0.30319"},{"name":"x-powered-by","value":"ASP.NET"},{"name":"date","value":"Tue, 11 Oct 2016 20:26:56 GMT"},{"name":"content-length","value":"0"}],"cookies":[]}},{"startedDateTime":"2016-10-11T20:34:34.022Z","pageref":2,"time":31.364999998360872,"timings":{"blocked":-1,"connect":1.474999999627471,"dns":-1,"receive":7.554999999701977,"send":0.919999998062849,"wait":21.415000000968575},"cache":{"beforeRequest":null,"afterRequest":null},"request":{"method":"DELETE","url":"http://localhost/WebApiDemo/employee/1000","httpVersion":"HTTP/1.1","headersSize":110,"bodySize":0,"postData":{"mimeType":"application/x-www-form-urlencoded","text":"","params":[]},"headers":[],"queryString":[],"cookies":[]},"response":{"status":200,"statusText":"OK","httpVersion":"HTTP/1.1","redirectURL":"","headersSize":368,"bodySize":0,"content":{"size":0,"mimeType":"application/octet-stream","text":""},"headers":[{"name":"cache-control","value":"no-cache"},{"name":"pragma","value":"no-cache"},{"name":"expires","value":"-1"},{"name":"server","value":"Microsoft-IIS/10.0"},{"name":"x-aspnet-version","value":"4.0.30319"},{"name":"x-powered-by","value":"ASP.NET"},{"name":"date","value":"Tue, 11 Oct 2016 20:34:34 GMT"},{"name":"content-length","value":"0"}],"cookies":[]}},{"startedDateTime":"2016-10-11T21:03:50.094Z","pageref":3,"time":29.97500000335276,"timings":{"blocked":-1,"connect":1.5850000027567148,"dns":-1,"receive":7.855000000447035,"send":0.9250000007450581,"wait":19.609999999403954},"cache":{"beforeRequest":null,"afterRequest":null},"request":{"method":"DELETE","url":"http://localhost/WebApiDemo/employee/1000","httpVersion":"HTTP/1.1","headersSize":110,"bodySize":0,"postData":{"mimeType":"application/x-www-form-urlencoded","text":"","params":[]},"headers":[],"queryString":[],"cookies":[]},"response":{"status":200,"statusText":"OK","httpVersion":"HTTP/1.1","redirectURL":"","headersSize":368,"bodySize":0,"content":{"size":0,"mimeType":"application/octet-stream","text":""},"headers":[{"name":"cache-control","value":"no-cache"},{"name":"pragma","value":"no-cache"},{"name":"expires","value":"-1"},{"name":"server","value":"Microsoft-IIS/10.0"},{"name":"x-aspnet-version","value":"4.0.30319"},{"name":"x-powered-by","value":"ASP.NET"},{"name":"date","value":"Tue, 11 Oct 2016 21:03:50 GMT"},{"name":"content-length","value":"0"}],"cookies":[]}},{"startedDateTime":"2016-10-11T21:03:54.506Z","pageref":4,"time":17.539999997243285,"timings":{"blocked":-1,"connect":1.4899999983608723,"dns":-1,"receive":11.070000000298023,"send":1.150000000372529,"wait":3.8299999982118607},"cache":{"beforeRequest":null,"afterRequest":null},"request":{"method":"DELETE","url":"http://localhost/WebApiDemo/employee/1000","httpVersion":"HTTP/1.1","headersSize":110,"bodySize":0,"postData":{"mimeType":"application/x-www-form-urlencoded","text":"","params":[]},"headers":[],"queryString":[],"cookies":[]},"response":{"status":404,"statusText":"Not Found","httpVersion":"HTTP/1.1","redirectURL":"","headersSize":462,"bodySize":66,"content":{"size":66,"mimeType":"application/json","text":"{\"Message\":\"Employee not found!\"}"},"headers":[{"name":"cache-control","value":"no-cache"},{"name":"pragma","value":"no-cache"},{"name":"content-type","value":"application/json; charset=utf-8"},{"name":"expires","value":"-1"},{"name":"server","value":"Microsoft-IIS/10.0"},{"name":"x-aspnet-version","value":"4.0.30319"},{"name":"x-powered-by","value":"ASP.NET"},{"name":"date","value":"Tue, 11 Oct 2016 21:03:54 GMT"},{"name":"content-length","value":"33"}],"cookies":[]}},{"startedDateTime":"2016-10-11T21:16:07.243Z","pageref":5,"time":30.899999998509884,"timings":{"blocked":-1,"connect":2.1600000001490116,"dns":-1,"receive":8.955000001937151,"send":0.9749999977648258,"wait":18.809999998658895},"cache":{"beforeRequest":null,"afterRequest":null},"request":{"method":"DELETE","url":"http://localhost/WebApiDemo/employee/1000","httpVersion":"HTTP/1.1","headersSize":110,"bodySize":0,"postData":{"mimeType":"application/x-www-form-urlencoded","text":"","params":[]},"headers":[],"queryString":[],"cookies":[]},"response":{"status":200,"statusText":"OK","httpVersion":"HTTP/1.1","redirectURL":"","headersSize":368,"bodySize":0,"content":{"size":0,"mimeType":"application/octet-stream","text":""},"headers":[{"name":"cache-control","value":"no-cache"},{"name":"pragma","value":"no-cache"},{"name":"expires","value":"-1"},{"name":"server","value":"Microsoft-IIS/10.0"},{"name":"x-aspnet-version","value":"4.0.30319"},{"name":"x-powered-by","value":"ASP.NET"},{"name":"date","value":"Tue, 11 Oct 2016 21:16:07 GMT"},{"name":"content-length","value":"0"}],"cookies":[]}},{"startedDateTime":"2016-10-11T21:20:50.094Z","pageref":6,"time":53.79999999701977,"timings":{"blocked":-1,"connect":1.7650000005960464,"dns":-1,"receive":7.3049999959766865,"send":0.955000001937151,"wait":43.774999998509884},"cache":{"beforeRequest":null,"afterRequest":null},"request":{"method":"DELETE","url":"http://localhost/WebApiDemo/employee/1000","httpVersion":"HTTP/1.1","headersSize":110,"bodySize":0,"postData":{"mimeType":"application/x-www-form-urlencoded","text":"","params":[]},"headers":[],"queryString":[],"cookies":[]},"response":{"status":200,"statusText":"OK","httpVersion":"HTTP/1.1","redirectURL":"","headersSize":368,"bodySize":0,"content":{"size":0,"mimeType":"application/octet-stream","text":""},"headers":[{"name":"cache-control","value":"no-cache"},{"name":"pragma","value":"no-cache"},{"name":"expires","value":"-1"},{"name":"server","value":"Microsoft-IIS/10.0"},{"name":"x-aspnet-version","value":"4.0.30319"},{"name":"x-powered-by","value":"ASP.NET"},{"name":"date","value":"Tue, 11 Oct 2016 21:20:50 GMT"},{"name":"content-length","value":"0"}],"cookies":[]}},{"startedDateTime":"2016-10-12T17:51:51.470Z","pageref":7,"time":37.12000001966953,"timings":{"blocked":-1,"connect":2.5350000113248825,"dns":-1,"receive":7.560000017285347,"send":0.875,"wait":26.149999991059303},"cache":{"beforeRequest":null,"afterRequest":null},"request":{"method":"DELETE","url":"http://localhost/WebApiDemo/employee/1000","httpVersion":"HTTP/1.1","headersSize":110,"bodySize":0,"postData":{"mimeType":"application/x-www-form-urlencoded","text":"","params":[]},"headers":[],"queryString":[],"cookies":[]},"response":{"status":200,"statusText":"OK","httpVersion":"HTTP/1.1","redirectURL":"","headersSize":368,"bodySize":0,"content":{"size":0,"mimeType":"application/octet-stream","text":""},"headers":[{"name":"cache-control","value":"no-cache"},{"name":"pragma","value":"no-cache"},{"name":"expires","value":"-1"},{"name":"server","value":"Microsoft-IIS/10.0"},{"name":"x-aspnet-version","value":"4.0.30319"},{"name":"x-powered-by","value":"ASP.NET"},{"name":"date","value":"Wed, 12 Oct 2016 17:51:51 GMT"},{"name":"content-length","value":"0"}],"cookies":[]}}]},"name":"Delete Employee 1000"},{"order":0,"url":"http://localhost/WebApiDemo/employee","method":"PUT","type":"saved","referenceEntry":2,"updateTime":1476220554853,"id":294,"kind":"ARC#RequestObject","har":{"comment":"Created when making a request as a history object.","version":"1.2","creator":{"comment":"ARC for Google Chrome.","version":"5.0.5-test","name":"Advanced REST client"},"browser":{"version":"53.0.2785.143","name":"Chrome"},"pages":[{"startedDateTime":"2016-10-11T20:52:45.544Z","id":"PUT:http://localhost/WebApiDemo/employee-0","title":"Update Employee 1000","pageTimings":{"onLoad":-1,"onContentLoad":-1}},{"startedDateTime":"2016-10-11T21:03:15.861Z","id":"PUT:http://localhost/WebApiDemo/employee-1","title":"Update Employee 1000","pageTimings":{"onLoad":-1,"onContentLoad":-1}},{"startedDateTime":"2016-10-11T21:03:15.865Z","id":"PUT:http://localhost/WebApiDemo/employee-2","title":"Update Employee 1000","pageTimings":{"onLoad":-1,"onContentLoad":-1}},{"startedDateTime":"2016-10-11T21:03:17.903Z","id":"PUT:http://localhost/WebApiDemo/employee-3","title":"Update Employee 1000","pageTimings":{"onLoad":-1,"onContentLoad":-1}},{"startedDateTime":"2016-10-11T21:15:54.825Z","id":"PUT:http://localhost/WebApiDemo/employee-4","title":"Update Employee 1000","pageTimings":{"onLoad":-1,"onContentLoad":-1}}],"entries":[{"startedDateTime":"2016-10-11T20:51:34.517Z","pageref":"PUT:http://localhost/WebApiDemo/employee-0","time":195.13000000081956,"timings":{"blocked":-1,"connect":1.3900000024586916,"dns":-1,"receive":9.56499999947846,"send":1.4999999981373549,"wait":182.67500000074506},"cache":{"beforeRequest":null,"afterRequest":null},"request":{"method":"PUT","url":"http://localhost/WebApiDemo/employee","httpVersion":"HTTP/1.1","headersSize":152,"bodySize":810,"postData":{"mimeType":"application/json","text":"{\n\"Id\": 1000,\n\"FirstName\": \"Alan\",\n\"LastName\": \"Newbeguy\",\n\"Department\": \"QA\",\n\"HireDateTime\": \"2016-10-11T11:46:00\",\n\"PhoneWork\": \"(555) 322-4455\",\n\"PhoneHome\": \"(555) 334-2334\",\n\"PhoneCell\": \"(555) 322-3395\",\n\"EmployeeType\": 2,\n\"DateOfBirth\": \"1964-07-19T00:00:00\",\n\"Email\": \"alan.newbeguy@yahoo.com\",\n\"StreetAddress\": \"602 New Address Street\",\n\"City\": \"San Francisco\",\n\"State\": \"CA\",\n\"ZipCode\": 97334\n}","params":[]},"headers":[{"name":"Content-Type","value":"application/json"}],"queryString":[],"cookies":[]},"response":{"status":201,"statusText":"Created","httpVersion":"HTTP/1.1","redirectURL":"","headersSize":472,"bodySize":0,"content":{"size":0,"mimeType":"application/octet-stream","text":""},"headers":[{"name":"cache-control","value":"no-cache"},{"name":"pragma","value":"no-cache"},{"name":"expires","value":"-1"},{"name":"location","value":"http://localhost/WebApiDemo/employee/1000"},{"name":"server","value":"Microsoft-IIS/10.0"},{"name":"x-aspnet-version","value":"4.0.30319"},{"name":"x-powered-by","value":"ASP.NET"},{"name":"date","value":"Tue, 11 Oct 2016 20:51:34 GMT"},{"name":"content-length","value":"0"}],"cookies":[]}},{"startedDateTime":"2016-10-11T20:51:34.517Z","pageref":1,"time":195.13000000081956,"timings":{"blocked":-1,"connect":1.3900000024586916,"dns":-1,"receive":9.56499999947846,"send":1.4999999981373549,"wait":182.67500000074506},"cache":{"beforeRequest":null,"afterRequest":null},"request":{"method":"PUT","url":"http://localhost/WebApiDemo/employee","httpVersion":"HTTP/1.1","headersSize":152,"bodySize":806,"postData":{"mimeType":"application/json","text":"{\n\"Id\": 1000,\n\"FirstName\": \"Alan\",\n\"LastName\": \"Newbeguy\",\n\"Department\": \"QA\",\n\"HireDateTime\": \"2016-10-11T11:46:00\",\n\"PhoneWork\": \"(555) 322-4455\",\n\"PhoneHome\": \"(555) 334-2334\",\n\"PhoneCell\": \"(555) 322-3395\",\n\"EmployeeType\": 2,\n\"DateOfBirth\": \"1964-07-19T00:00:00\",\n\"Email\": \"alan.newbeguy@yahoo.com\",\n\"StreetAddress\": \"602 New Abode Street\",\n\"City\": \"San Francisco\",\n\"State\": \"CA\",\n\"ZipCode\": 97334\n}","params":[]},"headers":[{"name":"Content-Type","value":"application/json"}],"queryString":[],"cookies":[]},"response":{"status":201,"statusText":"Created","httpVersion":"HTTP/1.1","redirectURL":"","headersSize":472,"bodySize":0,"content":{"size":0,"mimeType":"application/octet-stream","text":""},"headers":[{"name":"cache-control","value":"no-cache"},{"name":"pragma","value":"no-cache"},{"name":"expires","value":"-1"},{"name":"location","value":"http://localhost/WebApiDemo/employee/1000"},{"name":"server","value":"Microsoft-IIS/10.0"},{"name":"x-aspnet-version","value":"4.0.30319"},{"name":"x-powered-by","value":"ASP.NET"},{"name":"date","value":"Tue, 11 Oct 2016 20:51:34 GMT"},{"name":"content-length","value":"0"}],"cookies":[]}},{"startedDateTime":"2016-10-11T20:51:34.517Z","pageref":2,"time":195.13000000081956,"timings":{"blocked":-1,"connect":1.3900000024586916,"dns":-1,"receive":9.56499999947846,"send":1.4999999981373549,"wait":182.67500000074506},"cache":{"beforeRequest":null,"afterRequest":null},"request":{"method":"PUT","url":"http://localhost/WebApiDemo/employee","httpVersion":"HTTP/1.1","headersSize":152,"bodySize":806,"postData":{"mimeType":"application/json","text":"{\n\"Id\": 1000,\n\"FirstName\": \"Alan\",\n\"LastName\": \"Newbeguy\",\n\"Department\": \"QA\",\n\"HireDateTime\": \"2016-10-11T11:46:00\",\n\"PhoneWork\": \"(555) 322-4455\",\n\"PhoneHome\": \"(555) 334-2334\",\n\"PhoneCell\": \"(555) 322-3395\",\n\"EmployeeType\": 2,\n\"DateOfBirth\": \"1964-07-19T00:00:00\",\n\"Email\": \"alan.newbeguy@yahoo.com\",\n\"StreetAddress\": \"602 New Abode Street\",\n\"City\": \"San Francisco\",\n\"State\": \"CA\",\n\"ZipCode\": 97334\n}","params":[]},"headers":[{"name":"Content-Type","value":"application/json"}],"queryString":[],"cookies":[]},"response":{"status":201,"statusText":"Created","httpVersion":"HTTP/1.1","redirectURL":"","headersSize":472,"bodySize":0,"content":{"size":0,"mimeType":"application/octet-stream","text":""},"headers":[{"name":"cache-control","value":"no-cache"},{"name":"pragma","value":"no-cache"},{"name":"expires","value":"-1"},{"name":"location","value":"http://localhost/WebApiDemo/employee/1000"},{"name":"server","value":"Microsoft-IIS/10.0"},{"name":"x-aspnet-version","value":"4.0.30319"},{"name":"x-powered-by","value":"ASP.NET"},{"name":"date","value":"Tue, 11 Oct 2016 20:51:34 GMT"},{"name":"content-length","value":"0"}],"cookies":[]}},{"startedDateTime":"2016-10-11T21:03:17.818Z","pageref":3,"time":33.580000000074506,"timings":{"blocked":-1,"connect":1.5750000029802322,"dns":-1,"receive":9.074999997392297,"send":0.969999996945262,"wait":21.960000002756715},"cache":{"beforeRequest":null,"afterRequest":null},"request":{"method":"PUT","url":"http://localhost/WebApiDemo/employee","httpVersion":"HTTP/1.1","headersSize":152,"bodySize":806,"postData":{"mimeType":"application/json","text":"{\n\"Id\": 1000,\n\"FirstName\": \"Alan\",\n\"LastName\": \"Newbeguy\",\n\"Department\": \"QA\",\n\"HireDateTime\": \"2016-10-11T11:46:00\",\n\"PhoneWork\": \"(555) 322-4455\",\n\"PhoneHome\": \"(555) 334-2334\",\n\"PhoneCell\": \"(555) 322-3395\",\n\"EmployeeType\": 2,\n\"DateOfBirth\": \"1964-07-19T00:00:00\",\n\"Email\": \"alan.newbeguy@yahoo.com\",\n\"StreetAddress\": \"602 New Abode Street\",\n\"City\": \"San Francisco\",\n\"State\": \"CA\",\n\"ZipCode\": 97334\n}","params":[]},"headers":[{"name":"Content-Type","value":"application/json"}],"queryString":[],"cookies":[]},"response":{"status":200,"statusText":"OK","httpVersion":"HTTP/1.1","redirectURL":"","headersSize":368,"bodySize":0,"content":{"size":0,"mimeType":"application/octet-stream","text":""},"headers":[{"name":"cache-control","value":"no-cache"},{"name":"pragma","value":"no-cache"},{"name":"expires","value":"-1"},{"name":"server","value":"Microsoft-IIS/10.0"},{"name":"x-aspnet-version","value":"4.0.30319"},{"name":"x-powered-by","value":"ASP.NET"},{"name":"date","value":"Tue, 11 Oct 2016 21:03:17 GMT"},{"name":"content-length","value":"0"}],"cookies":[]}},{"startedDateTime":"2016-10-11T21:15:54.743Z","pageref":4,"time":30.50000000372529,"timings":{"blocked":-1,"connect":1.530000001192093,"dns":-1,"receive":8.564999997615814,"send":0.9700000025331974,"wait":19.435000002384186},"cache":{"beforeRequest":null,"afterRequest":null},"request":{"method":"PUT","url":"http://localhost/WebApiDemo/employee","httpVersion":"HTTP/1.1","headersSize":152,"bodySize":806,"postData":{"mimeType":"application/json","text":"{\n\"Id\": 1000,\n\"FirstName\": \"Alan\",\n\"LastName\": \"Newbeguy\",\n\"Department\": \"QA\",\n\"HireDateTime\": \"2016-10-11T11:46:00\",\n\"PhoneWork\": \"(555) 322-4455\",\n\"PhoneHome\": \"(555) 334-2334\",\n\"PhoneCell\": \"(555) 322-3395\",\n\"EmployeeType\": 2,\n\"DateOfBirth\": \"1964-07-19T00:00:00\",\n\"Email\": \"alan.newbeguy@yahoo.com\",\n\"StreetAddress\": \"602 New Abode Street\",\n\"City\": \"San Francisco\",\n\"State\": \"CA\",\n\"ZipCode\": 97334\n}","params":[]},"headers":[{"name":"Content-Type","value":"application/json"}],"queryString":[],"cookies":[]},"response":{"status":200,"statusText":"OK","httpVersion":"HTTP/1.1","redirectURL":"","headersSize":368,"bodySize":0,"content":{"size":0,"mimeType":"application/octet-stream","text":""},"headers":[{"name":"cache-control","value":"no-cache"},{"name":"pragma","value":"no-cache"},{"name":"expires","value":"-1"},{"name":"server","value":"Microsoft-IIS/10.0"},{"name":"x-aspnet-version","value":"4.0.30319"},{"name":"x-powered-by","value":"ASP.NET"},{"name":"date","value":"Tue, 11 Oct 2016 21:15:54 GMT"},{"name":"content-length","value":"0"}],"cookies":[]}}]},"name":"Update Employee 1000"}],"projects":[{"order":0,"requestIds":[279,281,285,287,289,290,290,292,293,294,294],"name":"WebAPI Demo (Employee)","created":1476204815897,"updateTime":1476309779312,"id":11,"kind":"ARC#ProjectObject"}]}